MANIFEST.in
README.md
setup.py
streamlit_iframe_autoresize/__init__.py
streamlit_iframe_autoresize.egg-info/PKG-INFO
streamlit_iframe_autoresize.egg-info/SOURCES.txt
streamlit_iframe_autoresize.egg-info/dependency_links.txt
streamlit_iframe_autoresize.egg-info/requires.txt
streamlit_iframe_autoresize.egg-info/top_level.txt
streamlit_iframe_autoresize/frontend/build/asset-manifest.json
streamlit_iframe_autoresize/frontend/build/fee7cee.js
streamlit_iframe_autoresize/frontend/build/index.html
streamlit_iframe_autoresize/frontend/build/static/js/2.c3678f2e.chunk.js
streamlit_iframe_autoresize/frontend/build/static/js/2.c3678f2e.chunk.js.LICENSE.txt
streamlit_iframe_autoresize/frontend/build/static/js/2.c3678f2e.chunk.js.map
streamlit_iframe_autoresize/frontend/build/static/js/main.80850d15.chunk.js
streamlit_iframe_autoresize/frontend/build/static/js/main.80850d15.chunk.js.map
streamlit_iframe_autoresize/frontend/build/static/js/runtime-main.d36a7741.js
streamlit_iframe_autoresize/frontend/build/static/js/runtime-main.d36a7741.js.map