Metadata-Version: 2.1
Name: streamlit-iframe-autoresize
Version: 0.0.1
Home-page: https://github.com/pragmatic-streamlit/streamlit-iframe-autoresize
Classifier: Intended Audience :: Developers
Classifier: Intended Audience :: Science/Research
Classifier: Programming Language :: Python :: 3
Classifier: Programming Language :: Python :: 3.6
Classifier: Programming Language :: Python :: 3.7
Classifier: Programming Language :: Python :: 3.8
Classifier: Programming Language :: Python :: 3.9
Classifier: Programming Language :: Python :: 3.10
Classifier: License :: OSI Approved
Classifier: Topic :: Scientific/Engineering
Requires-Dist: streamlit
